datus_postgresql/__init__.py
datus_postgresql/config.py
datus_postgresql/connector.py
datus_postgresql-0.1.0.dist-info/METADATA
datus_postgresql-0.1.0.dist-info/WHEEL
datus_postgresql-0.1.0.dist-info/entry_points.txt
datus_postgresql-0.1.0.dist-info/RECORD
